narcapi/__init__.py
narcapi/package.py
narcapi-0.0.3.dist-info/METADATA
narcapi-0.0.3.dist-info/WHEEL
narcapi-0.0.3.dist-info/licenses/LICENSE
narcapi-0.0.3.dist-info/RECORD
